jiralogreporter/__init__.py
jiralogreporter/__main__.py
jiralogreporter/_version.py
jiralogreporter/cli.py
jiralogreporter/reporter.py
jiralogreporter-0.0.1.dist-info/LICENSE
jiralogreporter-0.0.1.dist-info/METADATA
jiralogreporter-0.0.1.dist-info/WHEEL
jiralogreporter-0.0.1.dist-info/entry_points.txt
jiralogreporter-0.0.1.dist-info/top_level.txt
jiralogreporter-0.0.1.dist-info/RECORD
