Metadata-Version: 2.1
Name: jiralogreporter
Version: 0.0.1
Summary: A kubernetes shell
Home-page: https://github.com/vshn/jiralogreporter
Author: João Pinto
Author-email: joao.pinto@vshn.ch
License: BSD-3
Platform: UNKNOWN
Requires-Dist: click
